authenticator/__init__.py
Squad1CoreAuthenticator-1.5.3.dist-info/METADATA
Squad1CoreAuthenticator-1.5.3.dist-info/WHEEL
Squad1CoreAuthenticator-1.5.3.dist-info/top_level.txt
Squad1CoreAuthenticator-1.5.3.dist-info/RECORD
