Metadata-Version: 2.1
Name: Squad1CoreAuthenticator
Version: 1.5.3
Summary: paquete utilizado para autenticar mensajes.
Home-page: https://github.com/matiasfelau/authenticator
Author: matiasfelau
Author-email: matiasfelau@gmail.com
Classifier: Programming Language :: Python :: 3
Classifier: License :: OSI Approved :: MIT License
Classifier: Operating System :: OS Independent
Requires-Python: >=3.6
Requires-Dist: pika
